deep_vars/__init__.py
deep_vars/deep_vars.py
deep_vars/py.typed
deep_vars/version.py
deep_vars/handlers/__init__.py
deep_vars/handlers/_base.py
deep_vars/handlers/_container.py
deep_vars/handlers/callable.py
deep_vars/handlers/hide.py
deep_vars/handlers/loop.py
deep_vars/handlers/loop_dict.py
deep_vars/handlers/process.py
deep_vars/handlers/show.py
deep_vars-1.0.0.dist-info/METADATA
deep_vars-1.0.0.dist-info/WHEEL
deep_vars-1.0.0.dist-info/RECORD
