Metadata-Version: 2.1
Name: deep-vars
Version: 1.0.0
Summary: Recursive `vars` for all objects.
Project-URL: Homepage, https://github.com/vsego/deep-vars
Project-URL: Bug Tracker, https://github.com/vsego/deep-vars/issues
Project-URL: Changelog, https://github.com/vsego/deep-vars/blob/master/CHANGELOG.md
Author-email: Vedran Sego <vsego@vsego.org>
License-Expression: MIT
Classifier: Operating System :: OS Independent
Classifier: Programming Language :: Python :: 3.10
Classifier: Programming Language :: Python :: 3.11
Classifier: Typing :: Typed
Requires-Python: >=3.10
